setup.py
maec_to_stix/__init__.py
maec_to_stix.egg-info/PKG-INFO
maec_to_stix.egg-info/SOURCES.txt
maec_to_stix.egg-info/dependency_links.txt
maec_to_stix.egg-info/requires.txt
maec_to_stix.egg-info/top_level.txt
maec_to_stix/scripts/copy_maec_to_stix_config.py
maec_to_stix/scripts/maec_extract_indicators.py
maec_to_stix/scripts/maec_wrap.py
maec_to_stix/indicator_extractor/__init__.py
maec_to_stix/indicator_extractor/config_parser.py
maec_to_stix/indicator_extractor/indicator_filter.py
maec_to_stix/scripts/copy_maec_to_stix_config.py
maec_to_stix/scripts/maec_extract_indicators.py
maec_to_stix/scripts/maec_wrap.py
maec_to_stix/stix_wrapper/__init__.py
maec_to_stix/test/__init__.py
maec_to_stix/test/indicator_extractor/__init__.py
maec_to_stix/test/indicator_extractor/indicator_extractor_test.py
maec_to_stix/test/stix_wrapper/__init__.py
maec_to_stix/test/stix_wrapper/stix_wrapper_test.py