Metadata-Version: 1.0
Name: maec_to_stix
Version: 1.0.0-alpha1
Summary: An API for wrapping MAEC documents in STIX and also extracting STIX Indicators from MAEC documents.
Home-page: http://maec.mitre.org
Author: MAEC Project
Author-email: maec@mitre.org
License: UNKNOWN
Platform: UNKNOWN
Classifier: Programming Language :: Python
Classifier: Development Status :: 4 - Beta
Classifier: Intended Audience :: Developers
Classifier: License :: OSI Approved :: BSD License
Classifier: Operating System :: OS Independent
